AUTHORS
CHANGES
LICENSE
MANIFEST.in
README.rst
setup.py
django_simple_menu2.egg-info/PKG-INFO
django_simple_menu2.egg-info/SOURCES.txt
django_simple_menu2.egg-info/dependency_links.txt
django_simple_menu2.egg-info/requires.txt
django_simple_menu2.egg-info/top_level.txt
menu/__init__.py
menu/templates/bootstrap-navbar.html
menu/templatetags/__init__.py
menu/templatetags/menu.py