Metadata-Version: 1.1
Name: django-simple-menu2
Version: 2.0.7
Summary: Simple, yet powerful, code-based menus for Django applications
Home-page: https://github.com/trbs/django-simple-menu
Author: Evan Borgstrom
Author-email: evan@fatbox.ca
License: UNKNOWN
Platform: UNKNOWN
Classifier: Development Status :: 5 - Production/Stable
Classifier: Framework :: Django
Classifier: Intended Audience :: Developers
Classifier: License :: OSI Approved :: BSD License
Classifier: Natural Language :: English
Classifier: Topic :: Software Development :: Libraries
Classifier: Topic :: Software Development :: Libraries :: Python Modules
